{
  "_day": "2025-12-19",
  "checkedIn": {
    "brandon_ullom": {
      "inAt": "2025-12-19T15:37:50.098Z",
      "status": "WITH_GUEST",
      "ups": 1,
      "appts": 0,
      "delivered": 0,
      "turned": 0,
      "lastAssignedAt": "2025-12-19T21:02:37.367Z"
    },
    "brock_cross": {
      "inAt": "2025-12-19T15:49:50.513Z",
      "status": "AVAILABLE",
      "ups": 0,
      "appts": 0,
      "delivered": 0,
      "turned": 0,
      "lastAssignedAt": null
    },
    "eric_shirley": {
      "inAt": null,
      "status": "AVAILABLE",
      "ups": 0,
      "appts": 0,
      "delivered": 0,
      "turned": 0,
      "lastAssignedAt": null
    },
    "john_squier": {
      "inAt": "2025-12-19T18:23:46.492Z",
      "status": "AVAILABLE",
      "ups": 0,
      "appts": 0,
      "delivered": 0,
      "turned": 0,
      "lastAssignedAt": null
    },
    "parker_mcwhirter": {
      "inAt": "2025-12-19T15:49:53.667Z",
      "status": "AVAILABLE",
      "ups": 0,
      "appts": 0,
      "delivered": 0,
      "turned": 0,
      "lastAssignedAt": null
    },
    "rob_vanderbeek": {
      "inAt": "2025-12-19T15:49:52.087Z",
      "status": "AVAILABLE",
      "ups": 0,
      "appts": 0,
      "delivered": 0,
      "turned": 0,
      "lastAssignedAt": null
    },
    "veronica_nekrassoff": {
      "inAt": "2025-12-19T15:34:02.299Z",
      "status": "WITH_GUEST",
      "ups": 0,
      "appts": 0,
      "delivered": 0,
      "turned": 0,
      "lastAssignedAt": null
    }
  },
  "rotation": [
    "veronica_nekrassoff",
    "brock_cross",
    "rob_vanderbeek",
    "parker_mcwhirter",
    "john_squier",
    "brandon_ullom"
  ],
  "log": [
    {
      "ts": "2025-12-19T21:02:37.367Z",
      "type": "assign",
      "advisorId": "brandon_ullom",
      "advisorName": "Brandon Ullom",
      "meta": {
        "source": "Walk-in",
        "guest": "",
        "notes": ""
      }
    },
    {
      "ts": "2025-12-19T21:02:31.842Z",
      "type": "status",
      "advisorId": "brandon_ullom",
      "advisorName": "Brandon Ullom",
      "meta": {
        "status": "AVAILABLE"
      }
    },
    {
      "ts": "2025-12-19T18:23:46.492Z",
      "type": "check_in",
      "advisorId": "john_squier",
      "advisorName": "John Squier",
      "meta": {}
    },
    {
      "ts": "2025-12-19T17:37:37.334Z",
      "type": "status",
      "advisorId": "veronica_nekrassoff",
      "advisorName": "Veronica Nekrassoff",
      "meta": {
        "status": "WITH_GUEST"
      }
    },
    {
      "ts": "2025-12-19T17:37:34.097Z",
      "type": "status",
      "advisorId": "brandon_ullom",
      "advisorName": "Brandon Ullom",
      "meta": {
        "status": "WITH_GUEST"
      }
    },
    {
      "ts": "2025-12-19T15:49:53.667Z",
      "type": "check_in",
      "advisorId": "parker_mcwhirter",
      "advisorName": "Parker McWhirter",
      "meta": {}
    },
    {
      "ts": "2025-12-19T15:49:52.087Z",
      "type": "check_in",
      "advisorId": "rob_vanderbeek",
      "advisorName": "Rob Vanderbeek",
      "meta": {}
    },
    {
      "ts": "2025-12-19T15:49:50.513Z",
      "type": "check_in",
      "advisorId": "brock_cross",
      "advisorName": "Brock Cross",
      "meta": {}
    },
    {
      "ts": "2025-12-19T15:37:50.098Z",
      "type": "check_in",
      "advisorId": "brandon_ullom",
      "advisorName": "Brandon Ullom",
      "meta": {}
    },
    {
      "ts": "2025-12-19T15:34:02.299Z",
      "type": "check_in",
      "advisorId": "veronica_nekrassoff",
      "advisorName": "Veronica Nekrassoff",
      "meta": {}
    },
    {
      "ts": "2025-12-19T15:33:58.209Z",
      "type": "reset_day",
      "advisorId": "",
      "advisorName": "",
      "meta": {}
    }
  ],
  "settings": {
    "markWithGuestOnAssign": true
  },
  "__serverUpdatedAt": ""
}